LICENSE
README.md
pyproject.toml
setup.py
rd_undetected_chromedriver.egg-info/PKG-INFO
rd_undetected_chromedriver.egg-info/SOURCES.txt
rd_undetected_chromedriver.egg-info/dependency_links.txt
rd_undetected_chromedriver.egg-info/requires.txt
rd_undetected_chromedriver.egg-info/top_level.txt
undetected_chromedriver/__init__.py
undetected_chromedriver/cdp.py
undetected_chromedriver/devtool.py
undetected_chromedriver/dprocess.py
undetected_chromedriver/options.py
undetected_chromedriver/patcher.py
undetected_chromedriver/reactor.py
undetected_chromedriver/webelement.py