Metadata-Version: 2.1
Name: rd-undetected-chromedriver
Version: 3.5.5
Summary: Selenium.webdriver.Chrome replacement with compatiblity for Brave, and other Chromium based browsers.Not triggered by CloudFlare/Imperva/hCaptcha and such.NOTE: results may vary due to many factors. No guarantees are given, except for ongoing efforts in understanding detection algorithms.
Home-page: https://github.com/ultrafunkamsterdam/undetected-chromedriver
Author: UltrafunkAmsterdam
Author-email: UltrafunkAmsterdam <info@blackhat-security.nl>, JiangXiaoqiang <jiangtingqiang@gmail.com>
License: GPL-3.0
Project-URL: Homepage, https://github.com/ultrafunkamsterdam/undetected-chromedriver
Classifier: License :: OSI Approved :: GNU General Public License v3 (GPLv3)
Classifier: Programming Language :: Python :: 3
Classifier: Programming Language :: Python :: 3.10
Classifier: Programming Language :: Python :: 3.11
Classifier: Programming Language :: Python :: 3.7
Classifier: Programming Language :: Python :: 3.8
Classifier: Programming Language :: Python :: 3.9
Requires-Python: >=3.10
License-File: LICENSE
Requires-Dist: requests
Requires-Dist: selenium>=4.9.0
Requires-Dist: websockets
Requires-Dist: twine>=4.0.2
